README.md
setup.py
go2pod/__init__.py
go2pod/action.py
go2pod/cli.py
go2pod/config.py
go2pod/const.py
go2pod/docker.py
go2pod/ensure.py
go2pod/exc.py
go2pod/kube.py
go2pod/patch.py
go2pod/template.py
go2pod/utils.py
go2pod.egg-info/PKG-INFO
go2pod.egg-info/SOURCES.txt
go2pod.egg-info/dependency_links.txt
go2pod.egg-info/entry_points.txt
go2pod.egg-info/requires.txt
go2pod.egg-info/top_level.txt
go2pod/cmds/__init__.py
go2pod/cmds/all_.py
go2pod/cmds/build.py
go2pod/cmds/deploy.py
go2pod/cmds/init.py
go2pod/cmds/prepare.py
go2pod/templates/go2pod.yml.template
go2pod/templates/pod.yaml.template